cycle_gan/__init__.py
cycle_gan/dataset.py
cycle_gan/losses.py
cycle_gan/model.py
cycle_gan/sampler.py
cycle_gan/utils.py
tests/__init__.py
tests/test_dataset.py
tests/test_losses.py
tests/test_model.py
tests/test_sampler.py
tests/test_utils.py
delira_cycle_gan-0.1.1.dist-info/LICENSE
delira_cycle_gan-0.1.1.dist-info/METADATA
delira_cycle_gan-0.1.1.dist-info/WHEEL
delira_cycle_gan-0.1.1.dist-info/top_level.txt
delira_cycle_gan-0.1.1.dist-info/RECORD
