Metadata-Version: 2.1
Name: delira-cycle-gan
Version: 0.1.1
Summary: UNKNOWN
Home-page: https://github.com/justusschock/delira_cycle_gan_pytorch
Author: Justus Schock
Author-email: justus.schock@rwth-aachen.de
License: BSD 2-Clause License
Requires-Dist: delira[torch] (>=0.3.1)
Requires-Dist: torch (>=1.0.1)
